[
    {
        "email": "chandrikadevassy6122@gmail.com",
        "dob": "2013-10-08"
    },
    {
        "email": "rakeshjayaram8269@gmail.com",
        "dob": "2005-08-16"
    },
    {
        "email": "devurangaswamy1325@gmail.com",
        "dob": "2009-09-06"
    },
    {
        "email": "nikhilaiyer9939@gmail.com",
        "dob": "2008-03-19"
    },
    {
        "email": "harikrishnankurian3853@gmail.com",
        "dob": "2009-04-14"
    },
    {
        "email": "sreekanthpanicker5254@gmail.com",
        "dob": "2004-01-15"
    },
    {
        "email": "renjithmangalathu9669@gmail.com",
        "dob": "2008-01-09"
    },
    {
        "email": "surajjoseph5942@gmail.com",
        "dob": "2014-05-09"
    },
    {
        "email": "deepashanavas6691@gmail.com",
        "dob": "2013-08-12"
    },
    {
        "email": "akashhariharan3848@gmail.com",
        "dob": "2012-10-22"
    }
]